iprir/__init__.py
iprir/afrinic.txt
iprir/api.py
iprir/apnic.txt
iprir/arin.txt
iprir/database.py
iprir/iprir.sqlite
iprir/ipset.py
iprir/lactic.txt
iprir/parser.py
iprir/record.py
iprir/ripencc.txt
iprir/tests.py
iprir/updater.py
iprir/utils.py
iprir/__pycache__/__init__.cpython-34.pyc
iprir/__pycache__/api.cpython-34.pyc
iprir/__pycache__/database.cpython-34.pyc
iprir/__pycache__/ipset.cpython-34.pyc
iprir/__pycache__/parser.cpython-34.pyc
iprir/__pycache__/record.cpython-34.pyc
iprir/__pycache__/updater.cpython-34.pyc
iprir/__pycache__/utils.cpython-34.pyc
iprir-0.3.0.dev0.dist-info/DESCRIPTION.rst
iprir-0.3.0.dev0.dist-info/METADATA
iprir-0.3.0.dev0.dist-info/RECORD
iprir-0.3.0.dev0.dist-info/WHEEL
iprir-0.3.0.dev0.dist-info/metadata.json
iprir-0.3.0.dev0.dist-info/pbr.json
iprir-0.3.0.dev0.dist-info/top_level.txt
