Metadata-Version: 2.0
Name: iprir
Version: 0.3.0.dev0
Summary: Retrieve, store and query information about Regional Internet Registries
Home-page: https://github.com/account-login/iprir
Author: account-login
Author-email: UNKNOWN
License: MIT
Keywords: IP RIR
Platform: UNKNOWN
Classifier: Development Status :: 3 - Alpha
Classifier: Intended Audience :: Developers
Classifier: Topic :: Internet
Classifier: License :: OSI Approved :: MIT License
Classifier: Operating System :: OS Independent
Classifier: Programming Language :: Python :: 3 :: Only
Classifier: Programming Language :: Python :: 3.4
Classifier: Programming Language :: Python :: 3.5
Classifier: Programming Language :: Python :: 3.6
Requires-Dist: requests
